gpgin_cli/__init__.py
gpgin_cli/cli.py
gpgin_cli/gpgin.py
gpgin_cli/prolog.py
gpgin_cli/run.py
gpgin_cli/train.py
gpgin_cli-0.1.1.dist-info/licenses/LICENSE
gpgin_cli-0.1.1.dist-info/METADATA
gpgin_cli-0.1.1.dist-info/WHEEL
gpgin_cli-0.1.1.dist-info/entry_points.txt
gpgin_cli-0.1.1.dist-info/top_level.txt
gpgin_cli-0.1.1.dist-info/RECORD
