Metadata-Version: 2.4
Name: gpgin-cli
Version: 0.1.1
Summary: General Purpose Graph Isomorphism Network is a GNN architecture that is able to process graphs with continuous node and edge features.
Author-email: Umar Zein <umarzein1314@email.com>
License-Expression: MIT
Project-URL: Homepage, https://github.com/UmarZein/gpgin-cli
Requires-Python: >=3.8
License-File: LICENSE
Requires-Dist: torch>=2.0.0
Requires-Dist: torch-geometric>=2.5.0
Requires-Dist: rdkit>=2022.09.5
Requires-Dist: numpy
Requires-Dist: tqdm
Dynamic: license-file
